MANIFEST.in
README.rst
setup.py
netbox_path/__init__.py
netbox_path/admin.py
netbox_path/filtersets.py
netbox_path/forms.py
netbox_path/models.py
netbox_path/navigation.py
netbox_path/search.py
netbox_path/tables.py
netbox_path/template_content.py
netbox_path/urls.py
netbox_path/views.py
netbox_path.egg-info/PKG-INFO
netbox_path.egg-info/SOURCES.txt
netbox_path.egg-info/dependency_links.txt
netbox_path.egg-info/not-zip-safe
netbox_path.egg-info/top_level.txt
netbox_path/api/__init__.py
netbox_path/api/impact.py
netbox_path/api/serializers.py
netbox_path/api/urls.py
netbox_path/api/views.py
netbox_path/migrations/0001_initial.py
netbox_path/migrations/0002_alter_path_created_alter_path_custom_field_data_and_more.py
netbox_path/migrations/0003_path_image.py
netbox_path/migrations/__init__.py
netbox_path/static/netbox_path/index.css
netbox_path/static/netbox_path/index.js
netbox_path/static/netbox_path/sprite.svg
netbox_path/templates/netbox_path/device.html
netbox_path/templates/netbox_path/path.html
netbox_path/templates/netbox_path/rack.html
netbox_path/templates/netbox_path/region.html
netbox_path/templates/netbox_path/site.html
netbox_path/templates/netbox_path/virtualmachine.html
netbox_path/templates/netbox_path/vlan.html
tests/__init__.py