Metadata-Version: 2.1
Name: netbox-path
Version: 0.3.6
Summary: Create visual and queryable maps of logical paths within your infrastructure
Home-page: https://github.com/sol1/netbox-path
License: UNKNOWN
Platform: UNKNOWN
